vectorian_core.cpython-38-x86_64-linux-gnu.so
vectorian/metrics.py
vectorian/_version.py
vectorian/index.py
vectorian/__init__.py
vectorian/importers.py
vectorian/interact.py
vectorian/embeddings.py
vectorian/normalization.py
vectorian/alignment.py
vectorian/session.py
vectorian/saliency.py
vectorian/tqdm.py
vectorian/core/__init__.py
vectorian/sim/vector.py
vectorian/sim/token.py
vectorian/sim/__init__.py
vectorian/sim/modifier.py
vectorian/sim/kernel.py
vectorian/sim/span.py
vectorian/render/sankey.py
vectorian/render/matrix.py
vectorian/render/__init__.py
vectorian/render/utils.py
vectorian/render/vega.py
vectorian/render/location.py
vectorian/render/excerpt.py
vectorian/render/render.py
vectorian/corpus/__init__.py
vectorian/corpus/corpus.py
vectorian/corpus/document.py
vectorian-0.9.15.dist-info/LICENSE.txt
vectorian-0.9.15.dist-info/RECORD
vectorian-0.9.15.dist-info/top_level.txt
vectorian-0.9.15.dist-info/WHEEL
vectorian-0.9.15.dist-info/METADATA
