Metadata-Version: 2.1
Name: vectorian
Version: 0.9.15
Summary: UNKNOWN
Home-page: UNKNOWN
Author: Bernhard Liebl
Author-email: liebl@informatik.uni-leipzig.de
License: GPLv2
Platform: UNKNOWN
License-File: LICENSE.txt
Requires-Dist: pybind11 (~=2.6.2)
Requires-Dist: pyalign (>=0.3.6)
Requires-Dist: smart-open (<4.0.0,>=3.0.0)
Requires-Dist: tqdm (>=4.56.2)
Requires-Dist: spacy (>=3.0.0)
Requires-Dist: fasttext (>=0.9.2)
Requires-Dist: compress-fasttext (>=0.0.6)
Requires-Dist: awesome-slugify (>=1.6.5)
Requires-Dist: roman (>=3.3)
Requires-Dist: yattag (>=1.14.0)
Requires-Dist: download (>=0.3.5)
Requires-Dist: cached-property (>=1.5.2)
Requires-Dist: gensim (<4.0.0,>=3.8.3)
Requires-Dist: cachetools (>=4.2.2)
